[
  {
    "date": "2026-03-17",
    "regime": "\ud83d\udfe1 Mixed Signals",
    "signals": {
      "SPY_below_200MA": false,
      "SPY_above_200MA": true,
      "QQQ_above_100MA": false,
      "ARKK_3mo_drop": false,
      "VIX_over_25": false,
      "VIX_under_20": false,
      "TNX_above_4": true,
      "TNX_below_3": false,
      "OVX_low": false,
      "OVX_high": true,
      "OVX_mid": false
    }
  },
  {
    "date": "2026-03-18",
    "regime": "\ud83d\udfe1 Mixed Signals",
    "signals": {
      "SPY_below_200MA": false,
      "SPY_above_200MA": true,
      "QQQ_above_100MA": false,
      "ARKK_3mo_drop": false,
      "VIX_over_25": false,
      "VIX_under_20": false,
      "TNX_above_4": true,
      "TNX_below_3": false,
      "OVX_low": false,
      "OVX_high": true,
      "OVX_mid": false
    }
  },
  {
    "date": "2026-03-19",
    "regime": "\ud83d\udfe1 Mixed Signals",
    "signals": {
      "SPY_below_200MA": false,
      "SPY_above_200MA": true,
      "QQQ_above_100MA": false,
      "ARKK_3mo_drop": false,
      "VIX_over_25": true,
      "VIX_under_20": false,
      "TNX_above_4": true,
      "TNX_below_3": false,
      "OVX_low": false,
      "OVX_high": true,
      "OVX_mid": false
    }
  },
  {
    "date": "2026-03-20",
    "regime": "\ud83d\udfe1 Mixed Signals",
    "signals": {
      "SPY_below_200MA": true,
      "SPY_above_200MA": false,
      "QQQ_above_100MA": false,
      "ARKK_3mo_drop": false,
      "VIX_over_25": false,
      "VIX_under_20": false,
      "TNX_above_4": true,
      "TNX_below_3": false,
      "OVX_low": false,
      "OVX_high": true,
      "OVX_mid": false
    }
  },
  {
    "date": "2026-03-23",
    "regime": "\ud83d\udd34 Downturn Risk",
    "signals": {
      "SPY_below_200MA": true,
      "SPY_above_200MA": false,
      "QQQ_above_100MA": false,
      "ARKK_3mo_drop": false,
      "VIX_over_25": true,
      "VIX_under_20": false,
      "TNX_above_4": true,
      "TNX_below_3": false,
      "OVX_low": false,
      "OVX_high": true,
      "OVX_mid": false
    }
  },
  {
    "date": "2026-03-24",
    "regime": "\ud83d\udd34 Downturn Risk",
    "signals": {
      "SPY_below_200MA": true,
      "SPY_above_200MA": false,
      "QQQ_above_100MA": false,
      "ARKK_3mo_drop": false,
      "VIX_over_25": true,
      "VIX_under_20": false,
      "TNX_above_4": true,
      "TNX_below_3": false,
      "OVX_low": false,
      "OVX_high": false,
      "OVX_mid": true
    }
  },
  {
    "date": "2026-03-25",
    "regime": "\ud83d\udd34 Downturn Risk",
    "signals": {
      "SPY_below_200MA": true,
      "SPY_above_200MA": false,
      "QQQ_above_100MA": false,
      "ARKK_3mo_drop": true,
      "VIX_over_25": true,
      "VIX_under_20": false,
      "TNX_above_4": true,
      "TNX_below_3": false,
      "OVX_low": false,
      "OVX_high": false,
      "OVX_mid": true
    }
  },
  {
    "date": "2026-03-26",
    "regime": "\ud83d\udd34 Downturn Risk",
    "signals": {
      "SPY_below_200MA": true,
      "SPY_above_200MA": false,
      "QQQ_above_100MA": false,
      "ARKK_3mo_drop": false,
      "VIX_over_25": true,
      "VIX_under_20": false,
      "TNX_above_4": true,
      "TNX_below_3": false,
      "OVX_low": false,
      "OVX_high": true,
      "OVX_mid": false
    }
  },
  {
    "date": "2026-03-27",
    "regime": "\ud83d\udd34 Downturn Risk",
    "signals": {
      "SPY_below_200MA": true,
      "SPY_above_200MA": false,
      "QQQ_above_100MA": false,
      "ARKK_3mo_drop": true,
      "VIX_over_25": true,
      "VIX_under_20": false,
      "TNX_above_4": true,
      "TNX_below_3": false,
      "OVX_low": false,
      "OVX_high": true,
      "OVX_mid": false
    }
  }
]