{
  "SPY": {
    "price": 733.83,
    "ma200": 672.4
  },
  "QQQ": {
    "price": 695.77,
    "ma100": 616.73
  },
  "ARKK": {
    "three_month_change_percent": 19.98
  },
  "VIX": {
    "level": 17.39
  },
  "TNX": {
    "yield": 4.36
  },
  "OVX": {
    "level": 72.34,
    "regime": "mid"
  },
  "mortgage": {
    "rate": 6.37,
    "condition": "Neutral"
  },
  "income_spread": {
    "sp_div_yield": 1.01,
    "ten_year_yield": 4.36,
    "spread": -3.35,
    "regime": "Bond Yield Advantage"
  }
}